pleco/__init__.py
pleco/__main__.py
pleco_cli-1.1.0.post4.dist-info/METADATA
pleco_cli-1.1.0.post4.dist-info/WHEEL
pleco_cli-1.1.0.post4.dist-info/entry_points.txt
pleco_cli-1.1.0.post4.dist-info/licenses/LICENSE
pleco_cli-1.1.0.post4.dist-info/RECORD
