Metadata-Version: 2.4
Name: pleco-cli
Version: 1.1.0.post4
Summary: Read in and clean ROV serial data from serial ports
Author-email: Robert Ward II <robert.ward@noaa.gov>
License: 'Software code created by U.S. Government employees is not subject to copyright in the United States (17 U.S.C.§105). The United States/Department of Commerce reserve all rights to seek and obtain copyright protection in countries other than the United States for Software authored in its entirety by the Department of Commerce. To this end, the Department of Commerce hereby grants to Recipient a royalty-free, nonexclusive license to use,copy, and create derivative works of the Software o
License-File: LICENSE
Classifier: Programming Language :: Python :: 3
Requires-Python: >=3.13
Requires-Dist: pandas
Requires-Dist: pyserial
